setup.cfg
setup.py
pybone/__init__.py
pybone/board.py
pybone/config.py
pybone/pin_desc.py
pybone.egg-info/PKG-INFO
pybone.egg-info/SOURCES.txt
pybone.egg-info/dependency_links.txt
pybone.egg-info/top_level.txt
pybone/bone_3_8/__init__.py
pybone/bone_3_8/config.py
pybone/tests/__init__.py
pybone/tests/board.py
pybone/tests/utils/__init__.py
pybone/tests/utils/version.py
pybone/utils/__init__.py
pybone/utils/filesystem.py
pybone/utils/version.py