Metadata-Version: 1.1
Name: pybone
Version: 0.0.1.dev20140817185617
Summary: Python library for managing beagleboard hardware I/O
Home-page: https://github.com/njouanin/pybone
Author: UNKNOWN
Author-email: UNKNOWN
License: GPLv3
Platform: UNKNOWN
Classifier: Development Status :: 2 - Pre-Alpha
Classifier: Intended Audience :: Developers
Classifier: License :: OSI Approved :: GNU General Public License v3 (GPLv3)
Classifier: Operating System :: POSIX :: Linux
Classifier: Programming Language :: Python :: 3.4
Classifier: Topic :: System :: Hardware :: Hardware Drivers
Classifier: Topic :: System :: Operating System Kernels :: Linux
